braze/__init__.py
braze/apps.py
braze/client.py
braze/constants.py
braze/exceptions.py
braze/ace_channel/__init__.py
braze/ace_channel/braze_push_channel.py
braze/settings/__init__.py
braze/settings/common.py
braze/settings/devstack.py
braze/settings/production.py
braze/settings/test.py
edx_braze_client-1.1.3.dist-info/LICENSE
edx_braze_client-1.1.3.dist-info/LICENSE.txt
edx_braze_client-1.1.3.dist-info/METADATA
edx_braze_client-1.1.3.dist-info/WHEEL
edx_braze_client-1.1.3.dist-info/entry_points.txt
edx_braze_client-1.1.3.dist-info/top_level.txt
edx_braze_client-1.1.3.dist-info/RECORD
